AnonAutomator_arin17/__init__.py
AnonAutomator_arin17/__main__.py
AnonAutomator_arin17/modules.py
AnonAutomator_arin17/resources/messages.json
AnonAutomator_arin17-0.0.3.dist-info/LICENSE
AnonAutomator_arin17-0.0.3.dist-info/METADATA
AnonAutomator_arin17-0.0.3.dist-info/WHEEL
AnonAutomator_arin17-0.0.3.dist-info/top_level.txt
AnonAutomator_arin17-0.0.3.dist-info/RECORD
