Metadata-Version: 2.1
Name: AnonAutomator-arin17
Version: 0.0.3
Summary: A small test package for automated anonymous messaging
Author-email: Bishwajit Ghosh <arin17bishwa@gmail.com>
License: Copyright (c) 2018 The Python Packaging Authority        
Project-URL: Homepage, https://github.com/arin17bishwa/anon-msg-automator
Project-URL: Bug Tracker, https://github.com/arin17bishwa/anon-msg-automator/issues
Classifier: Programming Language :: Python :: 3
Classifier: License :: OSI Approved :: MIT License
Classifier: Operating System :: OS Independent
Requires-Python: >=3.7
License-File: LICENSE
Requires-Dist: requests
